main/__init__.py
looker2dbt-0.0.1.dist-info/LICENSE
looker2dbt-0.0.1.dist-info/METADATA
looker2dbt-0.0.1.dist-info/WHEEL
looker2dbt-0.0.1.dist-info/top_level.txt
looker2dbt-0.0.1.dist-info/RECORD
